nopynotion/__init__.py
nopynotion-0.2.9.dist-info/LICENSE
nopynotion-0.2.9.dist-info/METADATA
nopynotion-0.2.9.dist-info/WHEEL
nopynotion-0.2.9.dist-info/top_level.txt
nopynotion-0.2.9.dist-info/RECORD
