Metadata-Version: 2.1
Name: nopynotion
Version: 0.2.9
Summary: a warpper for notion to update data
Home-page: https://github.com/wuchangsheng951/nopynotion
Author: Huiming Sun
Author-email: sunhuiming55@gmail.com
License: UNKNOWN
Platform: UNKNOWN
Classifier: Programming Language :: Python :: 3
Classifier: License :: OSI Approved :: MIT License
Classifier: Operating System :: OS Independent
License-File: LICENSE
Requires-Dist: requests
